operator_precedence_high_roller/message_validator.py
operator_precedence_high_roller/computing/compute.py
operator_precedence_high_roller/json_handling/json_handle.py
operator_precedence_high_roller/json_handling/gambling/gamble.py
operator_precedence_high_roller/json_handling/roll_saving/roll_save.py
operator_precedence_high_roller/parsing/command_parser.py
operator_precedence_high_roller/parsing/command_token.py
operator_precedence_high_roller/parsing/input_buffer.py
operator_precedence_high_roller/parsing/lexical_analyzer.py
operator_precedence_high_roller/parsing/stacknode.py
operator_precedence_high_roller/parsing/enums/command_type.py
operator_precedence_high_roller/parsing/enums/token_type.py
operator_precedence_high_roller-1.2.1.dist-info/METADATA
operator_precedence_high_roller-1.2.1.dist-info/WHEEL
operator_precedence_high_roller-1.2.1.dist-info/RECORD
