Metadata-Version: 2.4
Name: operator_precedence_high_roller
Version: 1.2.1
Summary: dice command parser/roller discord bot
Project-URL: Homepage, https://github.com/jaderobertsg2019/Operator-Precedence-High-Roller
Author-email: Jade Roberts <jaderobertsg2019@gmail.com>
Classifier: License :: OSI Approved :: MIT License
Classifier: Operating System :: OS Independent
Classifier: Programming Language :: Python :: 3
Requires-Python: >=3.8
